{"GlobalPropertiesHash":"vfmQgTfehZGnQN8VYvsJh392SC4J+tB7Dj9mme61k+M=","FingerprintPatternsHash":"gq3WsqcKBUGTSNle7RKKyXRIwh7M8ccEqOqYvIzoM04=","PropertyOverridesHash":"8ZRc1sGeVrPBx4lD717BgRaQekyh78QKV9SKsdt638U=","InputHashes":["7EOkqiGGhqfAKNdAuDMVDPuFXPM2EFFmvTA/YfWjvtw=","kUaKU7hJTmIVOYHiAAMNwXM8DZe\u002B/n\u002BD70bP/9lg0f8=","DEm7ozFAAU2xOXtOh9p0D0OgiGEjtJLSpzVkS5PRzj8=","tWncE4i\u002B7IZGimHVayvkYsP0KMgeX6HCvPA\u002BxMBLCvY=","JwrK7ISTMdpfwuPhOShvgmp1zmqNm2GtVYop2dQJ9Rg=","JHCSmNQuh3gDe5HAv16HkRaIWxvVQHyZQwC2/SdzM2Y=","p0itHZv66NexDCEnQkIFCFywgv5SuaDyzbDYdmFjSME=","AyjALcVwOrPIqG6ckbRX4Rv1SGnxhV5m03aVETNJfLE=","Ihv6am94yMtgIc6aCFtGdzQf6LZsit3M9IyfJEp0EUs=","gQ9aRYrSMNpSCEJ6GbRDX63E5DDP58pAPFFrx5zIECg=","04WWfe7BTOS\u002B1gBaVNzxqmNKoEYFi26xy2idHa38bi8=","eYri0drg3VlbwX9GjZ0svzweiKANkoiermlUx45cftU=","RhqPl9/SbtAF46TvxbV029Z\u002BKRbpLTmKTnid7I88dHs=","Pwa9NLkgld/RjCoVGwB7ijUQG0ffilceWfhUj1ytzRY=","qL3NXW61bAslztAee83UTCMWsyouG/3KMUglOQHaCxQ=","6/aW41pwyLWLIUlK\u002BwGB4QcZpXmTD9cmRlQCHB9S2cM=","vRGUW3n5768\u002B6E3x9AFyocCtNtVwHShSZRXXcXh9Ue0=","gHphTuaitdvlNGg4pHbzooH9891peB8LJJIw\u002B\u002B5Wxio=","6an\u002B4IjT0FCURMguHI2hvWMvgwbS9\u002B4lMC4u8Kqf2f4="],"CachedAssets":{"tWncE4i\u002B7IZGimHVayvkYsP0KMgeX6HCvPA\u002BxMBLCvY=":{"Identity":"D:\\Workspace\\PRN222_Project\\AdressBookManagement\\AdressBookManagement\\wwwroot\\favicon.png","SourceId":"AdressBookManagement","SourceType":"Discovered","ContentRoot":"D:\\Workspace\\PRN222_Project\\AdressBookManagement\\AdressBookManagement\\wwwroot\\","BasePath":"_content/AdressBookManagement","RelativePath":"favicon#[.{fingerprint}]?.png","AssetKind":"All","AssetMode":"All","AssetRole":"Primary","AssetMergeBehavior":null,"AssetMergeSource":"","RelatedAsset":null,"AssetTraitName":null,"AssetTraitValue":null,"Fingerprint":"ifv42okdf2","Integrity":"4mWsDy3aHl36ZbGt8zByK7Pvd4kRUoNgTYzRnwmPHwg=","CopyToOutputDirectory":"Never","CopyToPublishDirectory":"PreserveNewest","OriginalItemSpec":"wwwroot\\favicon.png","FileLength":1148,"LastWriteTime":"2025-07-07T14:51:45.2320832+00:00"},"DEm7ozFAAU2xOXtOh9p0D0OgiGEjtJLSpzVkS5PRzj8=":{"Identity":"D:\\Workspace\\PRN222_Project\\AdressBookManagement\\AdressBookManagement\\wwwroot\\bootstrap\\bootstrap.min.css.map","SourceId":"AdressBookManagement","SourceType":"Discovered","ContentRoot":"D:\\Workspace\\PRN222_Project\\AdressBookManagement\\AdressBookManagement\\wwwroot\\","BasePath":"_content/AdressBookManagement","RelativePath":"bootstrap/bootstrap.min.css#[.{fingerprint}]?.map","AssetKind":"All","AssetMode":"All","AssetRole":"Primary","AssetMergeBehavior":null,"AssetMergeSource":"","RelatedAsset":null,"AssetTraitName":null,"AssetTraitValue":null,"Fingerprint":"8inm30yfxf","Integrity":"gBwg2tmA0Ci2u54gMF1jNCVku6vznarkLS6D76htNNQ=","CopyToOutputDirectory":"Never","CopyToPublishDirectory":"PreserveNewest","OriginalItemSpec":"wwwroot\\bootstrap\\bootstrap.min.css.map","FileLength":449111,"LastWriteTime":"2025-07-07T14:51:45.2320832+00:00"},"kUaKU7hJTmIVOYHiAAMNwXM8DZe\u002B/n\u002BD70bP/9lg0f8=":{"Identity":"D:\\Workspace\\PRN222_Project\\AdressBookManagement\\AdressBookManagement\\wwwroot\\bootstrap\\bootstrap.min.css","SourceId":"AdressBookManagement","SourceType":"Discovered","ContentRoot":"D:\\Workspace\\PRN222_Project\\AdressBookManagement\\AdressBookManagement\\wwwroot\\","BasePath":"_content/AdressBookManagement","RelativePath":"bootstrap/bootstrap.min#[.{fingerprint}]?.css","AssetKind":"All","AssetMode":"All","AssetRole":"Primary","AssetMergeBehavior":null,"AssetMergeSource":"","RelatedAsset":null,"AssetTraitName":null,"AssetTraitValue":null,"Fingerprint":"6gzpyzhau4","Integrity":"SiIVMGgRhdXjKSTIddX7mh9IbOXVcwQWc7/p4nS6D/0=","CopyToOutputDirectory":"Never","CopyToPublishDirectory":"PreserveNewest","OriginalItemSpec":"wwwroot\\bootstrap\\bootstrap.min.css","FileLength":162726,"LastWriteTime":"2025-07-07T14:51:45.2300963+00:00"},"7EOkqiGGhqfAKNdAuDMVDPuFXPM2EFFmvTA/YfWjvtw=":{"Identity":"D:\\Workspace\\PRN222_Project\\AdressBookManagement\\AdressBookManagement\\wwwroot\\app.css","SourceId":"AdressBookManagement","SourceType":"Discovered","ContentRoot":"D:\\Workspace\\PRN222_Project\\AdressBookManagement\\AdressBookManagement\\wwwroot\\","BasePath":"_content/AdressBookManagement","RelativePath":"app#[.{fingerprint}]?.css","AssetKind":"All","AssetMode":"All","AssetRole":"Primary","AssetMergeBehavior":null,"AssetMergeSource":"","RelatedAsset":null,"AssetTraitName":null,"AssetTraitValue":null,"Fingerprint":"da95v2qkru","Integrity":"u9qEka1auR7E3rd3/8/j8hkQdSOYj9bRJ4nYiFDR1sE=","CopyToOutputDirectory":"Never","CopyToPublishDirectory":"PreserveNewest","OriginalItemSpec":"wwwroot\\app.css","FileLength":2591,"LastWriteTime":"2025-07-07T14:51:45.2291208+00:00"}},"CachedCopyCandidates":{}}